obelisk/__init__.py
obelisk/exceptions.py
obelisk/py.typed
obelisk/asynchronous/__init__.py
obelisk/asynchronous/base.py
obelisk/asynchronous/client.py
obelisk/asynchronous/core.py
obelisk/strategies/__init__.py
obelisk/strategies/retry.py
obelisk/sync/__init__.py
obelisk/sync/client.py
obelisk/types/__init__.py
obelisk/types/core.py
obelisk_py-2.3.0.dist-info/METADATA
obelisk_py-2.3.0.dist-info/WHEEL
obelisk_py-2.3.0.dist-info/licenses/LICENSE
obelisk_py-2.3.0.dist-info/RECORD
