Metadata-Version: 2.4
Name: obelisk-py
Version: 2.3.0
Summary: The one Obelisk client to rule them all
Project-URL: source, https://github.com/predict-idlab/obelisk-python
Project-URL: documentation, https://predict-idlab.github.io/obelisk-python/
Project-URL: changelog, https://github.com/predict-idlab/obelisk-python/blob/main/CHANGELOG.rst
Author-email: Stef Pletinck <Stef.Pletinck@ugent.be>, Pieter Moens <Pieter.Moens@ugent.be>
License-File: LICENSE
Requires-Python: <3.14,>=3.10
Requires-Dist: httpx>=0.28.1
Requires-Dist: pydantic>=2.10.6
Requires-Dist: ruff>=0.9.6
